{
  "_comment": "Machine-readable regime state. Read by gate-check.sh before every buy. Updated by weekly-review (regime), EOD routine (P&L caps), midday (halt flag).",
  "regime": "EM-OUTFLOW-RISK-CAUTIOUS",
  "max_position_pct": 0.15,
  "max_gross_pct": 0.8,
  "max_new_trades_week": 3,
  "daily_pnl_pct": -0.28,
  "weekly_pnl_pct": -0.28,
  "peak_equity": 10026617500,
  "current_equity": 9949480000,
  "drawdown_from_peak_pct": -0.77,
  "trading_halted": false,
  "halt_reason": null,
  "updated": "2026-04-27"
}